README.rst
setup.py
prtogerrit/__init__.py
prtogerrit/bbclient.py
prtogerrit/clientbase.py
prtogerrit/cmd.py
prtogerrit/ghclient.py
prtogerrit.egg-info/PKG-INFO
prtogerrit.egg-info/SOURCES.txt
prtogerrit.egg-info/dependency_links.txt
prtogerrit.egg-info/entry_points.txt
prtogerrit.egg-info/not-zip-safe
prtogerrit.egg-info/requires.txt
prtogerrit.egg-info/top_level.txt