Metadata-Version: 1.1
Name: prtogerrit
Version: 1.0
Summary: Transfer pull requests to Gerrit
Home-page: http://bitbucket.org/zzzeek/prtogerrit
Author: Mike Bayer
Author-email: mike@zzzcomputing.com
License: MIT
Platform: UNKNOWN
Classifier: Development Status :: 4 - Beta
Classifier: Environment :: Console
Classifier: Programming Language :: Python
Classifier: Programming Language :: Python :: Implementation :: CPython
